nabudata/__init__.py
nabudata/datasets.py
nabudata/reconstructions/__init__.py
nabudata/reconstructions/mri_rec_astra.npz
nabudata/sinograms/__init__.py
nabudata/sinograms/mri_sino500.npz
nabudata/volumes/__init__.py
nabudata/volumes/mri_proj_astra.npz
nabudata-0.1.2.dist-info/LICENSE
nabudata-0.1.2.dist-info/METADATA
nabudata-0.1.2.dist-info/WHEEL
nabudata-0.1.2.dist-info/top_level.txt
nabudata-0.1.2.dist-info/zip-safe
nabudata-0.1.2.dist-info/RECORD
