Metadata-Version: 2.1
Name: nabudata
Version: 0.1.2
Summary: nabudata - test data for the nabu package
Home-page: UNKNOWN
Author: Pierre Paleo
Author-email: pierre.paleo@esrf.fr
Maintainer: Pierre Paleo
Maintainer-email: pierre.paleo@esrf.fr
License: UNKNOWN
Platform: UNKNOWN
Requires-Dist: numpy
